hk_utils/AttrDict.py
hk_utils/__init__.py
hk_utils/hk_print.py
hk_utils-1.1.7.dist-info/METADATA
hk_utils-1.1.7.dist-info/WHEEL
hk_utils-1.1.7.dist-info/top_level.txt
hk_utils-1.1.7.dist-info/RECORD
