Metadata-Version: 2.1
Name: hk-utils
Version: 1.1.7
Summary: Python utilities by Heekang Park
Home-page: https://github.com/HeekangPark/hk-utils
Author: Heekang Park
Author-email: park.heekang33@gmail.com
License: MIT
Classifier: Programming Language :: Python :: 3
Classifier: License :: OSI Approved :: MIT License
Classifier: Operating System :: OS Independent
Requires-Python: >=3
